[
  {
    "id": "a493296ed8e69268",
    "cluster_id": "c0108-fc01f7af",
    "title_original": "School shooting survivor sues AI gun detection firm after system failed to spot weapon",
    "url": "https://arstechnica.com/tech-policy/2026/06/school-shooting-survivor-sues-ai-gun-detection-firm-after-system-failed-to-spot-weapon/",
    "image_url": null,
    "source_id": "arstechnica",
    "source_name": "Ars Technica",
    "published": "2026-06-07T11:08:30+00:00",
    "fetched_at": "2026-06-07T15:25:08.061189+00:00",
    "cluster_size": 1,
    "also_covered_by": [],
    "summary_ko": "학교 총기 난사 생존자가 AI 총기 탐지 시스템이 무기를 감지하지 못했다며 해당 업체를 고소했습니다. 이 사건은 공공 안전 응용에서 AI 시스템의 정확도 기준을 어디까지 설정해야 하는지라는 근본적인 질문을 던지고 있습니다.",
    "insights_ko": [
      "생명 안전이 달린 AI 시스템의 법적 책임이 처음으로 사법부에서 판단되는 사례로, 향후 AI 제품의 성능 보증과 배포 기준에 선례를 남길 가능성이 있습니다.",
      "AI 탐지 시스템의 실패가 물리적 해를 끼친 직접적 인과관계 입증이 쟁점이 될 것으로 보이며, 이는 AI 시스템 제조사의 제품 책임(product liability) 범위를 재정의할 가능성이 있습니다.",
      "공공 안전 AI의 '충분한 정확도' 기준이 법적·규제적으로 명확히 정의되어야 한다는 압력이 강해질 것으로 예상되며, NIST나 정부 표준화 기구가 성능 임계값을 규정하도록 요구하는 후속 입법이 나올 수 있습니다."
    ],
    "category": "policy",
    "importance_score": 4
  }
]