{
  "concepts": null,
  "generated_at": "2026-07-08T00:24:11+00:00",
  "papers": {
    "enriched": 50,
    "enriched_pct": 8.5,
    "mentions": {
      "primary": 584,
      "reference": 3
    },
    "per_day_mentions": [
      {
        "day": "2026-06-04",
        "n": 20
      },
      {
        "day": "2026-06-05",
        "n": 17
      },
      {
        "day": "2026-06-06",
        "n": 2
      },
      {
        "day": "2026-06-08",
        "n": 24
      },
      {
        "day": "2026-06-09",
        "n": 21
      },
      {
        "day": "2026-06-10",
        "n": 22
      },
      {
        "day": "2026-06-11",
        "n": 22
      },
      {
        "day": "2026-06-12",
        "n": 21
      },
      {
        "day": "2026-06-13",
        "n": 1
      },
      {
        "day": "2026-06-15",
        "n": 27
      },
      {
        "day": "2026-06-16",
        "n": 25
      },
      {
        "day": "2026-06-17",
        "n": 30
      },
      {
        "day": "2026-06-18",
        "n": 30
      },
      {
        "day": "2026-06-19",
        "n": 31
      },
      {
        "day": "2026-06-23",
        "n": 29
      },
      {
        "day": "2026-06-24",
        "n": 32
      },
      {
        "day": "2026-06-25",
        "n": 28
      },
      {
        "day": "2026-06-26",
        "n": 29
      },
      {
        "day": "2026-06-29",
        "n": 30
      },
      {
        "day": "2026-06-30",
        "n": 30
      },
      {
        "day": "2026-07-02",
        "n": 31
      },
      {
        "day": "2026-07-03",
        "n": 45
      },
      {
        "day": "2026-07-06",
        "n": 1
      },
      {
        "day": "2026-07-07",
        "n": 39
      }
    ],
    "refs_pipe_7d": {
      "days_covered": 6,
      "rows": 4
    },
    "top_categories": [
      {
        "category": "cs.CV",
        "n": 12
      },
      {
        "category": "cs.CL",
        "n": 8
      },
      {
        "category": "cs.LG",
        "n": 7
      },
      {
        "category": "cs.AI",
        "n": 6
      },
      {
        "category": "cs.RO",
        "n": 6
      },
      {
        "category": "stat.ML",
        "n": 4
      },
      {
        "category": "stat.ME",
        "n": 3
      },
      {
        "category": "astro-ph.IM",
        "n": 1
      },
      {
        "category": "cs.CR",
        "n": 1
      },
      {
        "category": "cs.CY",
        "n": 1
      }
    ],
    "total": 587
  },
  "schema_version": 1
}
